<annotation>
  <folder>mine</folder>
  <filename>batch(169)</filename>
  <path>C:\Users\user\Desktop\mine\batch(169).jpg</path>
  <source>
    <database>Unknown</database>
  </source>
  <size>
    <width>4608</width>
    <height>3456</height>
    <depth>3</depth>
  </size>
  <segmented>0</segmented>
  <object>
    <name>nothealthy</name>
    <pose>Unspecified</pose>
    <truncated>0</truncated>
    <difficult>0</difficult>
    <bndbox>
      <xmin>1898</xmin>
      <ymin>2031</ymin>
      <xmax>2479</xmax>
      <ymax>2524</ymax>
    </bndbox>
  </object>
  <object>
    <name>nothealthy</name>
    <pose>Unspecified</pose>
    <truncated>0</truncated>
    <difficult>0</difficult>
    <bndbox>
      <xmin>998</xmin>
      <ymin>2153</ymin>
      <xmax>1683</xmax>
      <ymax>2742</ymax>
    </bndbox>
  </object>
  <object>
    <name>nothealthy</name>
    <pose>Unspecified</pose>
    <truncated>0</truncated>
    <difficult>0</difficult>
    <bndbox>
      <xmin>365</xmin>
      <ymin>2231</ymin>
      <xmax>1142</xmax>
      <ymax>2842</ymax>
    </bndbox>
  </object>
  <object>
    <name>nothealthy</name>
    <pose>Unspecified</pose>
    <truncated>0</truncated>
    <difficult>0</difficult>
    <bndbox>
      <xmin>387</xmin>
      <ymin>1342</ymin>
      <xmax>861</xmax>
      <ymax>1709</ymax>
    </bndbox>
  </object>
  <object>
    <name>nothealthy</name>
    <pose>Unspecified</pose>
    <truncated>0</truncated>
    <difficult>0</difficult>
    <bndbox>
      <xmin>2091</xmin>
      <ymin>1450</ymin>
      <xmax>2724</xmax>
      <ymax>1946</ymax>
    </bndbox>
  </object>
  <object>
    <name>nothealthy</name>
    <pose>Unspecified</pose>
    <truncated>0</truncated>
    <difficult>0</difficult>
    <bndbox>
      <xmin>2513</xmin>
      <ymin>1142</ymin>
      <xmax>3120</xmax>
      <ymax>1709</ymax>
    </bndbox>
  </object>
  <object>
    <name>nothealthy</name>
    <pose>Unspecified</pose>
    <truncated>0</truncated>
    <difficult>0</difficult>
    <bndbox>
      <xmin>3087</xmin>
      <ymin>1476</ymin>
      <xmax>3842</xmax>
      <ymax>2190</ymax>
    </bndbox>
  </object>
  <object>
    <name>nothealthy</name>
    <pose>Unspecified</pose>
    <truncated>0</truncated>
    <difficult>0</difficult>
    <bndbox>
      <xmin>2872</xmin>
      <ymin>1839</ymin>
      <xmax>3487</xmax>
      <ymax>2528</ymax>
    </bndbox>
  </object>
  <object>
    <name>nothealthy</name>
    <pose>Unspecified</pose>
    <truncated>0</truncated>
    <difficult>0</difficult>
    <bndbox>
      <xmin>2016</xmin>
      <ymin>2605</ymin>
      <xmax>2546</xmax>
      <ymax>3124</ymax>
    </bndbox>
  </object>
  <object>
    <name>nothealthy</name>
    <pose>Unspecified</pose>
    <truncated>0</truncated>
    <difficult>0</difficult>
    <bndbox>
      <xmin>1639</xmin>
      <ymin>3013</ymin>
      <xmax>2098</xmax>
      <ymax>3357</ymax>
    </bndbox>
  </object>
  <object>
    <name>nothealthy</name>
    <pose>Unspecified</pose>
    <truncated>0</truncated>
    <difficult>0</difficult>
    <bndbox>
      <xmin>2668</xmin>
      <ymin>2813</ymin>
      <xmax>3381</xmax>
      <ymax>3456</ymax>
    </bndbox>
  </object>
</annotation>
