<annotation>
  <folder>mine</folder>
  <filename>batch(166)</filename>
  <path>C:\Users\user\Desktop\mine\batch(166).jpg</path>
  <source>
    <database>Unknown</database>
  </source>
  <size>
    <width>4224</width>
    <height>5632</height>
    <depth>3</depth>
  </size>
  <segmented>0</segmented>
  <object>
    <name>nothealthy</name>
    <pose>Unspecified</pose>
    <truncated>0</truncated>
    <difficult>0</difficult>
    <bndbox>
      <xmin>183</xmin>
      <ymin>1278</ymin>
      <xmax>3708</xmax>
      <ymax>4122</ymax>
    </bndbox>
  </object>
  <object>
    <name>nothealthy</name>
    <pose>Unspecified</pose>
    <truncated>0</truncated>
    <difficult>0</difficult>
    <bndbox>
      <xmin>15</xmin>
      <ymin>2391</ymin>
      <xmax>1046</xmax>
      <ymax>5628</ymax>
    </bndbox>
  </object>
</annotation>
