<annotation>
  <folder>mine</folder>
  <filename>batch(311)</filename>
  <path>C:\Users\user\Desktop\mine\batch(311).jpg</path>
  <source>
    <database>Unknown</database>
  </source>
  <size>
    <width>4224</width>
    <height>5632</height>
    <depth>3</depth>
  </size>
  <segmented>0</segmented>
  <object>
    <name>healthy</name>
    <pose>Unspecified</pose>
    <truncated>0</truncated>
    <difficult>0</difficult>
    <bndbox>
      <xmin>1524</xmin>
      <ymin>1841</ymin>
      <xmax>2405</xmax>
      <ymax>2677</ymax>
    </bndbox>
  </object>
  <object>
    <name>nothealthy</name>
    <pose>Unspecified</pose>
    <truncated>0</truncated>
    <difficult>0</difficult>
    <bndbox>
      <xmin>538</xmin>
      <ymin>2368</ymin>
      <xmax>2024</xmax>
      <ymax>3799</ymax>
    </bndbox>
  </object>
  <object>
    <name>nothealthy</name>
    <pose>Unspecified</pose>
    <truncated>0</truncated>
    <difficult>0</difficult>
    <bndbox>
      <xmin>1827</xmin>
      <ymin>2716</ymin>
      <xmax>2935</xmax>
      <ymax>4077</ymax>
    </bndbox>
  </object>
  <object>
    <name>nothealthy</name>
    <pose>Unspecified</pose>
    <truncated>0</truncated>
    <difficult>0</difficult>
    <bndbox>
      <xmin>1043</xmin>
      <ymin>3543</ymin>
      <xmax>1899</xmax>
      <ymax>4374</ymax>
    </bndbox>
  </object>
  <object>
    <name>nothealthy</name>
    <pose>Unspecified</pose>
    <truncated>0</truncated>
    <difficult>0</difficult>
    <bndbox>
      <xmin>908</xmin>
      <ymin>1809</ymin>
      <xmax>1571</xmax>
      <ymax>2516</ymax>
    </bndbox>
  </object>
</annotation>
