<annotation>
  <folder>mine</folder>
  <filename>batch(236)</filename>
  <path>C:\Users\user\Desktop\mine\batch(236).jpg</path>
  <source>
    <database>Unknown</database>
  </source>
  <size>
    <width>4224</width>
    <height>5632</height>
    <depth>3</depth>
  </size>
  <segmented>0</segmented>
  <object>
    <name>nothealthy</name>
    <pose>Unspecified</pose>
    <truncated>0</truncated>
    <difficult>0</difficult>
    <bndbox>
      <xmin>121</xmin>
      <ymin>2228</ymin>
      <xmax>2633</xmax>
      <ymax>4634</ymax>
    </bndbox>
  </object>
  <object>
    <name>nothealthy</name>
    <pose>Unspecified</pose>
    <truncated>0</truncated>
    <difficult>0</difficult>
    <bndbox>
      <xmin>1996</xmin>
      <ymin>1347</ymin>
      <xmax>4090</xmax>
      <ymax>3772</ymax>
    </bndbox>
  </object>
  <object>
    <name>nothealthy</name>
    <pose>Unspecified</pose>
    <truncated>0</truncated>
    <difficult>0</difficult>
    <bndbox>
      <xmin>2290</xmin>
      <ymin>4209</ymin>
      <xmax>4215</xmax>
      <ymax>5591</ymax>
    </bndbox>
  </object>
</annotation>
